[
  {
    "cc": "5113407589711050|04|2027|170",
    "status": "Approved ✅",
    "site": "https://mwfdetectors.sg",
    "scheme": "",
    "type": "",
    "brand": "",
    "bank": "",
    "country": "",
    "proxy": false,
    "message": "Auth success🔥",
    "timestamp": "2025-10-28 06:03:05"
  },
  {
    "cc": "5113407589711050|04|2027|170",
    "status": "Approved ✅",
    "scheme": "MASTERCARD",
    "type": "PREPAID",
    "brand": "PREPAID MASTERCARD UNEMBOSSED NON US",
    "bank": "Peoples Trust Company",
    "country": "Canada",
    "proxy": "None",
    "timestamp": "2025-10-28 06:03:05"
  },
  {
    "cc": "5444224511575739|09|2029|192",
    "status": "Approved ✅",
    "site": "https://www.professionalwireless.com",
    "scheme": "",
    "type": "",
    "brand": "",
    "bank": "",
    "country": "",
    "proxy": false,
    "message": "Auth success🔥",
    "timestamp": "2025-10-29 06:03:28"
  },
  {
    "cc": "5444224511575739|09|2029|192",
    "status": "Approved ✅",
    "scheme": "MASTERCARD",
    "type": "DEBIT",
    "brand": "DEBIT STANDARD",
    "bank": "Js Bank Limited",
    "country": "Pakistan",
    "proxy": "None",
    "timestamp": "2025-10-29 06:03:29"
  },
  {
    "cc": "5444227300210855|08|2030|447",
    "status": "Approved ✅",
    "site": "https://lavanesso.com",
    "scheme": "",
    "type": "",
    "brand": "",
    "bank": "",
    "country": "",
    "proxy": false,
    "message": "Auth success🔥",
    "timestamp": "2025-10-29 06:03:37"
  },
  {
    "cc": "5444227300210855|08|2030|447",
    "status": "Approved ✅",
    "scheme": "MASTERCARD",
    "type": "DEBIT",
    "brand": "DEBIT STANDARD",
    "bank": "Js Bank Limited",
    "country": "Pakistan",
    "proxy": "None",
    "timestamp": "2025-10-29 06:03:37"
  },
  {
    "cc": "4154644400832995|10|2028|367",
    "status": "Approved ✅",
    "site": "https://funkyfain.com",
    "scheme": "",
    "type": "",
    "brand": "",
    "bank": "",
    "country": "",
    "proxy": false,
    "message": "Auth success🔥",
    "timestamp": "2025-10-29 06:03:42"
  },
  {
    "cc": "4154644400832995|10|2028|367",
    "status": "Approved ✅",
    "scheme": "VISA",
    "type": "DEBIT",
    "brand": "VISA CLASSIC",
    "bank": "Khaleeji Bank B.S.C",
    "country": "Bahrain",
    "proxy": "None",
    "timestamp": "2025-10-29 06:03:42"
  },
  {
    "cc": "5486974512136803|01|2026|903",
    "status": "Approved ✅",
    "site": "https://www.essancy.co.uk",
    "scheme": "",
    "type": "",
    "brand": "",
    "bank": "",
    "country": "",
    "proxy": false,
    "message": "Auth success🔥",
    "timestamp": "2025-10-29 06:03:56"
  },
  {
    "cc": "5486974512136803|01|2026|903",
    "status": "Approved ✅",
    "scheme": "MASTERCARD",
    "type": "CREDIT",
    "brand": "GOLD",
    "bank": "Dz Bank Ag Deutsche Zentral-Genossenschaftsbank",
    "country": "Germany",
    "proxy": "None",
    "timestamp": "2025-10-29 06:03:57"
  },
  {
    "cc": "5540259570443679|01|2028|835",
    "status": "Approved ✅",
    "site": "https://zanelladermacare.com",
    "scheme": "",
    "type": "",
    "brand": "",
    "bank": "",
    "country": "",
    "proxy": false,
    "message": "Auth success🔥",
    "timestamp": "2025-10-29 06:04:02"
  },
  {
    "cc": "5540259570443679|01|2028|835",
    "status": "Approved ✅",
    "scheme": "MASTERCARD",
    "type": "CREDIT",
    "brand": "STANDARD",
    "bank": "Mastercajas S.A.",
    "country": "Spain",
    "proxy": "None",
    "timestamp": "2025-10-29 06:04:02"
  },
  {
    "cc": "3750053540264111|02|2026|460",
    "status": "Approved ✅",
    "site": "https://k33b.com",
    "scheme": "",
    "type": "",
    "brand": "",
    "bank": "",
    "country": "",
    "proxy": false,
    "message": "Auth success🔥",
    "timestamp": "2025-10-29 06:04:19"
  },
  {
    "cc": "3750053540264111|02|2026|460",
    "status": "Approved ✅",
    "scheme": "AMERICAN EXPRESS",
    "type": "CREDIT",
    "brand": "STANDARD",
    "bank": "Unknown Bank",
    "country": "Germany",
    "proxy": "None",
    "timestamp": "2025-10-29 06:04:19"
  },
  {
    "cc": "3756019308128982|11|2027|651",
    "status": "Approved ✅",
    "site": "https://www.comfortq.it",
    "scheme": "",
    "type": "",
    "brand": "",
    "bank": "",
    "country": "",
    "proxy": false,
    "message": "Auth success🔥",
    "timestamp": "2025-10-29 06:04:30"
  },
  {
    "cc": "3756019308128982|11|2027|651",
    "status": "Approved ✅",
    "scheme": "AMERICAN EXPRESS",
    "type": "CREDIT",
    "brand": "STANDARD",
    "bank": "Unknown Bank",
    "country": "Spain",
    "proxy": "None",
    "timestamp": "2025-10-29 06:04:31"
  },
  {
    "cc": "5229625556737714|07|2028|513",
    "status": "Approved ✅",
    "site": "https://www.comfortq.it",
    "scheme": "",
    "type": "",
    "brand": "",
    "bank": "",
    "country": "",
    "proxy": false,
    "message": "Auth success🔥",
    "timestamp": "2025-10-29 06:04:38"
  },
  {
    "cc": "5229625556737714|07|2028|513",
    "status": "Approved ✅",
    "scheme": "MASTERCARD",
    "type": "DEBIT",
    "brand": "DEBIT STANDARD",
    "bank": "Ing Belgium",
    "country": "Belgium",
    "proxy": "None",
    "timestamp": "2025-10-29 06:04:38"
  },
  {
    "cc": "5126699576906793|01|2030|611",
    "status": "Approved ✅",
    "site": "https://www.escashopmirano.com",
    "scheme": "",
    "type": "",
    "brand": "",
    "bank": "",
    "country": "",
    "proxy": false,
    "message": "Auth success🔥",
    "timestamp": "2025-10-29 06:05:03"
  },
  {
    "cc": "5126699576906793|01|2030|611",
    "status": "Approved ✅",
    "scheme": "MASTERCARD",
    "type": "PREPAID",
    "brand": "PREPAID MASTERCARD UNEMBOSSED NON US",
    "bank": "Cassa Centrale Banca - Credito Cooperativo Del Nord Est Spa",
    "country": "Italy",
    "proxy": "None",
    "timestamp": "2025-10-29 06:05:03"
  },
  {
    "cc": "4165981803310469|09|2027|621",
    "status": "Approved ✅",
    "site": "https://k33b.com",
    "scheme": "",
    "type": "",
    "brand": "",
    "bank": "",
    "country": "",
    "proxy": false,
    "message": "Auth success🔥",
    "timestamp": "2025-10-29 06:05:11"
  },
  {
    "cc": "4165981803310469|09|2027|621",
    "status": "Approved ✅",
    "scheme": "VISA",
    "type": "DEBIT",
    "brand": "VISA INFINITE",
    "bank": "Revolut Bank Uab",
    "country": "Ireland",
    "proxy": "None",
    "timestamp": "2025-10-29 06:05:11"
  },
  {
    "cc": "5404500069402691|07|2027|836",
    "status": "Approved ✅",
    "site": "https://k33b.com",
    "scheme": "",
    "type": "",
    "brand": "",
    "bank": "",
    "country": "",
    "proxy": false,
    "message": "Auth success🔥",
    "timestamp": "2025-10-29 06:05:28"
  },
  {
    "cc": "5404500069402691|07|2027|836",
    "status": "Approved ✅",
    "scheme": "N/A",
    "type": "CREDIT",
    "brand": "MASTER",
    "bank": "APS FINANCIAL LIMITED",
    "country": "UNITED KINGDOM",
    "proxy": "None",
    "timestamp": "2025-10-29 06:05:29"
  },
  {
    "cc": "5404819217801780|10|2027|206",
    "status": "Approved ✅",
    "site": "https://www.essancy.co.uk",
    "scheme": "",
    "type": "",
    "brand": "",
    "bank": "",
    "country": "",
    "proxy": false,
    "message": "Auth success🔥",
    "timestamp": "2025-10-29 06:05:34"
  },
  {
    "cc": "5404819217801780|10|2027|206",
    "status": "Approved ✅",
    "scheme": "N/A",
    "type": "CREDIT",
    "brand": "MASTER",
    "bank": "DNB BANK ASA",
    "country": "NORWAY",
    "proxy": "None",
    "timestamp": "2025-10-29 06:05:35"
  }
]