{
  "7198590578": {
    "sites": {
      "https://karenstampercollage.com": {
        "accounts": [
          {
            "email": "ele59nu0qi@gmail.com",
            "username": "user_woc8zdx9",
            "password": "cvo7gv0z0c65"
          }
        ],
        "cookies": {},
        "payment_count": 2,
        "mode": "rotate",
        "raw_cookies": {},
        "stripe_pk": "pk_live_r2ddvqvelpLF7vhoNYOUDket",
        "stripe_nonce": "792cd9a277"
      },
      "https://meslo.com": {
        "accounts": [
          {
            "email": "gvjaim6r9y@gmail.com",
            "username": "user_tjti9vca",
            "password": "4dh8gc2k7dm5"
          }
        ],
        "cookies": {
          "wp_woocommerce_session_71cbb2b7030fc1c69321026456a90f52": "t_d457564489e9a8a01cdb66588f05c7%7C%7C1762086286%7C%7C1762082686%7C%7Cbe2904ffd447dc27181541190403afea",
          "PHPSESSID": "06q57qr2fjmpjfji64fbohqo8u"
        },
        "payment_count": 3,
        "mode": "rotate",
        "raw_cookies": {
          "wp_woocommerce_session_71cbb2b7030fc1c69321026456a90f52": "t_d457564489e9a8a01cdb66588f05c7%7C%7C1762086286%7C%7C1762082686%7C%7Cbe2904ffd447dc27181541190403afea",
          "PHPSESSID": "06q57qr2fjmpjfji64fbohqo8u"
        },
        "cookies_valid": true,
        "stripe_pk": "pk_live_51NuxOIBJ0yBaEtI7lfWgsGeCkfg2l38cVIJCIsTt1lzQjXKbuxQ8hgFjhDw3gbNtZh7RtgwpQ94o4Wo1bxpd4A1f00hvAOahVl",
        "stripe_nonce": "c4501a1337"
      },
      "https://thektlg.com": {
        "accounts": [
          {
            "email": "5pit5trwqf@gmail.com",
            "username": "user_s0etsa6h",
            "password": "fxitvyimeyrl"
          }
        ],
        "cookies": {
          "mailchimp_landing_site": "https%3A%2F%2Fthektlg.com%2Fmy-account%2F"
        },
        "payment_count": 1,
        "mode": "rotate",
        "raw_cookies": {
          "mailchimp_landing_site": "https%3A%2F%2Fthektlg.com%2Fmy-account%2F"
        }
      },
      "https://www.theartofaestheticsbeauty.uk": {
        "accounts": [],
        "cookies": null,
        "payment_count": 1,
        "mode": "rotate"
      },
      "https://bleurart.com": {
        "accounts": [],
        "cookies": null,
        "payment_count": 0,
        "mode": "rotate"
      },
      "https://www.fossilcave.com": {
        "accounts": [],
        "cookies": null,
        "payment_count": 1,
        "mode": "rotate"
      },
      "https://qissa.com.au": {
        "accounts": [
          {
            "email": "4rr59cfigi@gmail.com",
            "username": "user_v46rn5si",
            "password": "korj3l3p5va8"
          }
        ],
        "cookies": {
          "mailchimp_landing_site": "https%3A%2F%2Fqissa.com.au%2Fmy-account%2F"
        },
        "payment_count": 4,
        "mode": "rotate",
        "raw_cookies": {
          "mailchimp_landing_site": "https%3A%2F%2Fqissa.com.au%2Fmy-account%2F"
        },
        "stripe_pk": "pk_live_51P8JSjEDxuqucW2nrEBmPS3Kp1G0LCaAEyXNAQ8JhDr9UtGlKCSDXBc4xo2jrG9ntu37i0Y95y0FOhQMj5NC2bDY00S0JR1huW",
        "stripe_nonce": "ac464d10dc",
        "cookies_valid": true
      },
      "https://giantlovebear.com": {
        "accounts": [
          {
            "email": "79dy1vqa5q@gmail.com",
            "username": "user_752a4zvn",
            "password": "bhtc6rn4egme"
          }
        ],
        "cookies": {
          "vchideactivationmsg_vc11": "7.5",
          "wcpay_currency": "GBP_1",
          "tk_ai": "jetpack%3ATCiqsHo9eIZ2my1RX0C1kgqm"
        },
        "payment_count": 1,
        "mode": "rotate",
        "raw_cookies": {
          "vchideactivationmsg_vc11": "7.5",
          "wcpay_currency": "GBP_1",
          "tk_ai": "jetpack%3ATCiqsHo9eIZ2my1RX0C1kgqm"
        }
      },
      "https://lavanesso.com": {
        "accounts": [
          {
            "email": "zy89efxujn@gmail.com",
            "username": "user_s84rv6zy",
            "password": "oiyits2od5lv"
          }
        ],
        "cookies": {},
        "payment_count": 2,
        "mode": "rotate",
        "raw_cookies": {},
        "stripe_pk": "pk_live_51L6f31D0ptqnuWlI9euLATyar3eLXORwobBmZ8wDtEo91egIed7S5hZuRpELiPUeV5AaXQdRp64aR2ErnPJse5nm003bOzvdng",
        "stripe_nonce": "726768f6a9"
      },
      "https://branding.wequal.com": {
        "accounts": [
          {
            "email": "9jsilpuvam@gmail.com",
            "username": "user_qubirr5b",
            "password": "xndvipkwsmuc"
          }
        ],
        "cookies": {},
        "payment_count": 2,
        "mode": "rotate",
        "raw_cookies": {},
        "stripe_pk": "pk_live_51Om0YGS7CuEmRemywqrkbSi03TDKvY6Iw665bEcCIktgPqwx4SltAImBodh79LgQLZotev6rre91g9MfCEM4xy1100yqetGlTC",
        "stripe_nonce": "44120749b5"
      },
      "https://darlingtonsteam.com": {
        "accounts": [
          {
            "email": "d6v0y02qrc@gmail.com",
            "username": "user_dtvocebc",
            "password": "jas2ilocuhen"
          }
        ],
        "cookies": {},
        "payment_count": 1,
        "mode": "rotate",
        "raw_cookies": {}
      },
      "https://liebherr-pdf.com": {
        "accounts": [
          {
            "email": "humwyqthay@gmail.com",
            "username": "user_xh0qjxnq",
            "password": "y3ah9tjd7bnm"
          }
        ],
        "cookies": {
          "__cf_bm": "bUn9eXBkww5aei0TGjaLUPAs.jB74C4gSaAOL8Ltm0g-1761912239-1.0.1.1-03i0QDiGOWMaoNaTOtn9YJEt.GG_cqUt12mPVJoEZK5y4ZD6ZRN1FihLrEqU0xekUnLptp8MeFcfmJhKGiE4WMPM6qdPAZJV_.sLBVH85xQ"
        },
        "payment_count": 2,
        "mode": "rotate",
        "raw_cookies": {},
        "stripe_pk": "pk_live_gDqUyNgKKbZyihXb74vK1FpD",
        "stripe_nonce": "09fe2bcc04",
        "cookies_valid": true
      },
      "https://www.envirotents.com": {
        "accounts": [
          {
            "email": "crbmz2qsro@gmail.com",
            "username": "user_fuiji68x",
            "password": "ur45kwd99ta0"
          }
        ],
        "cookies": {},
        "payment_count": 1,
        "mode": "rotate",
        "raw_cookies": {},
        "stripe_pk": "pk_live_51OrLixBu2kFCQAzcYW2qySa32Sf50tCmTGotGu0DfxocSra3WAzDkVLh48paXvSaBcRfBWRGYq3PP9haWI6fAW0a00sVGl6dg6",
        "stripe_nonce": "fb210587df"
      },
      "https://norwayomega.com": {
        "accounts": [],
        "cookies": null,
        "payment_count": 1,
        "mode": "rotate"
      },
      "https://blackdotstore.com": {
        "accounts": [
          {
            "email": "hqu7ij0t1r@gmail.com",
            "username": "user_fuzbd1fe",
            "password": "2i2hxtzrm0pz"
          }
        ],
        "cookies": {
          "wordpress_sec_d70710b8a20f5a3a72be283bc4f387dd": "hqu7ij0t1r%7C1763122140%7CIUqrR6xaHBCasoQ38qfV7WP0UV8SqfLy6EhHUXhlrMj%7C7fab5273e9480c419dcd90d018bb0ec84935fef1786b7289b83f88c8f68c8343",
          "wordpress_logged_in_d70710b8a20f5a3a72be283bc4f387dd": "hqu7ij0t1r%7C1763122140%7CIUqrR6xaHBCasoQ38qfV7WP0UV8SqfLy6EhHUXhlrMj%7C852abeb0919c0d2fbd2340c8371209f8528ca8ad33dfe0ab03b822037305212b"
        },
        "payment_count": 1,
        "mode": "rotate",
        "raw_cookies": {
          "wordpress_sec_d70710b8a20f5a3a72be283bc4f387dd": "hqu7ij0t1r%7C1763122140%7CIUqrR6xaHBCasoQ38qfV7WP0UV8SqfLy6EhHUXhlrMj%7C7fab5273e9480c419dcd90d018bb0ec84935fef1786b7289b83f88c8f68c8343",
          "wordpress_logged_in_d70710b8a20f5a3a72be283bc4f387dd": "hqu7ij0t1r%7C1763122140%7CIUqrR6xaHBCasoQ38qfV7WP0UV8SqfLy6EhHUXhlrMj%7C852abeb0919c0d2fbd2340c8371209f8528ca8ad33dfe0ab03b822037305212b"
        },
        "stripe_pk": "pk_live_51Ns8WVL2M1lkEPULoUZkFP2jgsMiEGHBnk8Uqr2DQZwvmMLfIpNmmiUssJ6hOqqR5ilLxkFlQjCSn1X5B6ZtJVIZ00onDLYzeH",
        "stripe_nonce": "cb68445f03"
      },
      "https://1stchoicepooltables.co.uk": {
        "accounts": [
          {
            "email": "ak6xr2vej3@gmail.com",
            "username": "user_m9pif1lz",
            "password": "u405muohx5pc"
          }
        ],
        "cookies": {},
        "payment_count": 1,
        "mode": "rotate",
        "raw_cookies": {},
        "stripe_pk": "pk_live_51KjgjeKC5tyVXetDMEYJheJBK9QOTYIV2bAGt4UYjFnie1owEIuMDt3bojoVfjj0el1LhsnLZkhZQsiTcS8z5mtt00dniV0wAM",
        "stripe_nonce": "3c435a1296"
      },
      "https://fatbuddha.ca": {
        "accounts": [
          {
            "email": "grkja43gor@gmail.com",
            "username": "user_4hmh0xfg",
            "password": "y3vqsd9mb8tj"
          }
        ],
        "cookies": {
          "_lscache_vary": "a37bd291d7826c089442385092d99f04",
          "wordpress_logged_in_e3f8438ed0c0bc57e667b271b70fcf9e": "grkja43gor%7C1763123182%7CvDBcTM7f2SlZ8LA6ZdL0AgY3BYiCUExMH93tfNYRPIi%7C9bcaea82699301e5ba77a2bced403d557761797eb0b590d937b50abdac1d6edf",
          "wfwaf-authcookie-efd509352b321eac8e2f5bab04b7b935": "1317%7Cother%7Cread%7Ce8f796eb6bac12d44818094ac3ef5a7290d95ffc389ff83fa315ddea1c826e62",
          "wordpress_sec_e3f8438ed0c0bc57e667b271b70fcf9e": "grkja43gor%7C1763123182%7CvDBcTM7f2SlZ8LA6ZdL0AgY3BYiCUExMH93tfNYRPIi%7C0d5bbd4d77d4088e752c7c947a2b93bd12e6007844c49d01b7261312ea13477c"
        },
        "payment_count": 1,
        "mode": "rotate",
        "raw_cookies": {
          "_lscache_vary": "a37bd291d7826c089442385092d99f04",
          "wordpress_logged_in_e3f8438ed0c0bc57e667b271b70fcf9e": "grkja43gor%7C1763123182%7CvDBcTM7f2SlZ8LA6ZdL0AgY3BYiCUExMH93tfNYRPIi%7C9bcaea82699301e5ba77a2bced403d557761797eb0b590d937b50abdac1d6edf",
          "wfwaf-authcookie-efd509352b321eac8e2f5bab04b7b935": "1317%7Cother%7Cread%7Ce8f796eb6bac12d44818094ac3ef5a7290d95ffc389ff83fa315ddea1c826e62",
          "wordpress_sec_e3f8438ed0c0bc57e667b271b70fcf9e": "grkja43gor%7C1763123182%7CvDBcTM7f2SlZ8LA6ZdL0AgY3BYiCUExMH93tfNYRPIi%7C0d5bbd4d77d4088e752c7c947a2b93bd12e6007844c49d01b7261312ea13477c"
        },
        "stripe_pk": "pk_test_Met0XVfPox98dRjZRsVs06ZT",
        "stripe_nonce": "0d420bcf3a"
      },
      "https://beautyloungeallin1.co.uk": {
        "accounts": [
          {
            "email": "h25b96b0m2@gmail.com",
            "username": "user_c37q7kwz",
            "password": "69rgmjqosdka"
          }
        ],
        "cookies": {},
        "payment_count": 2,
        "mode": "rotate",
        "raw_cookies": {},
        "stripe_pk": "pk_test_51PQozFRqMznL6WfqNB98RguSBXM5xkEm4F5VuhvYn6xkudNVVvYthU69PIRQS4jsi5AuBbFz8kF2uMTjTOYjv3OS00ebDPfifG",
        "stripe_nonce": "4e966e8d23"
      },
      "https://billieatoms.com": {
        "accounts": [
          {
            "email": "djembsbynz@gmail.com",
            "username": "user_1oxtuk3g",
            "password": "lel00g2jx7t9"
          }
        ],
        "cookies": {
          "woocommerce_tax_country": "HK",
          "limit-control": "27cda04a-10be-4388-b0d2-ac6ef8ee46b7",
          "wordpress_logged_in_700f7c131232b8ccb6a96e8c86b6884d": "djembsbynz%7C1763121850%7CAF5FaYDy23J6Z2VZOvlfoynisGWiQaW65c9abUM8PDw%7Cbf5d6bfc431b9976f2e731bfe22cdda98f81a6699bae929678eb017c053e81c5",
          "wfwaf-authcookie-a51818bd3fbb54a3225be9e1156a8fed": "753%7Cother%7Cread%7C80d4c70feefbb3f00b37de622b395d2aa28e718fa4326aced2115acb2a6835b5",
          "wordpress_sec_700f7c131232b8ccb6a96e8c86b6884d": "djembsbynz%7C1763121850%7CAF5FaYDy23J6Z2VZOvlfoynisGWiQaW65c9abUM8PDw%7C3b02339998abd2420e3367ecc44283ea9fe95b7cc12c8f783378523990d08b1f",
          "_fbp": "fb.1.1761913838714.703545969.AQ"
        },
        "payment_count": 7,
        "mode": "rotate",
        "raw_cookies": {
          "woocommerce_tax_country": "HK",
          "limit-control": "27cda04a-10be-4388-b0d2-ac6ef8ee46b7",
          "wordpress_logged_in_700f7c131232b8ccb6a96e8c86b6884d": "djembsbynz%7C1763121850%7CAF5FaYDy23J6Z2VZOvlfoynisGWiQaW65c9abUM8PDw%7Cbf5d6bfc431b9976f2e731bfe22cdda98f81a6699bae929678eb017c053e81c5",
          "wfwaf-authcookie-a51818bd3fbb54a3225be9e1156a8fed": "753%7Cother%7Cread%7C80d4c70feefbb3f00b37de622b395d2aa28e718fa4326aced2115acb2a6835b5",
          "wordpress_sec_700f7c131232b8ccb6a96e8c86b6884d": "djembsbynz%7C1763121850%7CAF5FaYDy23J6Z2VZOvlfoynisGWiQaW65c9abUM8PDw%7C3b02339998abd2420e3367ecc44283ea9fe95b7cc12c8f783378523990d08b1f"
        },
        "stripe_pk": "pk_live_51MeJ66ErjkarzevjyWX5Dgo9yXZoSzWUI5sAfXQCebxuk8WVj4V8gDZkCLJ8MDjEnonii7mFMCPKTQMWxnYcmcHQ00Y4GVK2Tk",
        "stripe_nonce": "2f1b5fe0b9",
        "cookies_valid": true
      },
      "https://www.gibsonretriever.com": {
        "accounts": [
          {
            "email": "pf0cxgfbjc@gmail.com",
            "username": "user_31gga0ne",
            "password": "5fr5q06t1tcs"
          }
        ],
        "cookies": {
          "PHPSESSID": "b79e2e73afc8864b9f9696bfe2ab756a",
          "wordpress_logged_in_13dcd74a81a31bf6b5f3a5b6ce1ee493": "user_31gga0ne%7C1763122010%7C9KH9NN43xk47KYNUa0bvJWtad7Z8dxS4QyoRvyzICPs%7C5ec137884f594eb332045fea21aad3a430a90aaa52d3b17d5dbe5c9300e412b5",
          "wordpress_sec_13dcd74a81a31bf6b5f3a5b6ce1ee493": "user_31gga0ne%7C1763122010%7C9KH9NN43xk47KYNUa0bvJWtad7Z8dxS4QyoRvyzICPs%7C32dc39cad91087eb51af645d564682b46ffba1caf417ce2599d623c30ce5ecf4"
        },
        "payment_count": 5,
        "mode": "rotate",
        "raw_cookies": {
          "PHPSESSID": "b79e2e73afc8864b9f9696bfe2ab756a",
          "wordpress_logged_in_13dcd74a81a31bf6b5f3a5b6ce1ee493": "user_31gga0ne%7C1763122010%7C9KH9NN43xk47KYNUa0bvJWtad7Z8dxS4QyoRvyzICPs%7C5ec137884f594eb332045fea21aad3a430a90aaa52d3b17d5dbe5c9300e412b5",
          "wordpress_sec_13dcd74a81a31bf6b5f3a5b6ce1ee493": "user_31gga0ne%7C1763122010%7C9KH9NN43xk47KYNUa0bvJWtad7Z8dxS4QyoRvyzICPs%7C32dc39cad91087eb51af645d564682b46ffba1caf417ce2599d623c30ce5ecf4"
        },
        "stripe_pk": "pk_live_51PHlKALxzWxjsRgOamB0z0u7MXB8PUNXt9zBgujZpj9Samy5PUaH4iW9HrOtp8ZBRtKidlkN8YOHkNGTMf1bGD3F00tMTLaY4G",
        "stripe_nonce": "57fc7f8208",
        "cookies_valid": true
      },
      "https://www.escashopmirano.com": {
        "accounts": [
          {
            "email": "3m0dpwcqzi@gmail.com",
            "username": "user_whokjb2p",
            "password": "4hd6bhz5htnh"
          }
        ],
        "cookies": {
          "wordpress_sec_1beb83a295a571198e9b4ecc05e58d1b": "3m0dpwcqzi%7C1763122602%7CHRz1C5gLE0G1xJE0ihchxMIngg9XzxvkSwrgFdxZPNQ%7Cc275c7310d518e33ff8ac7658b5fe360766c844e8f88678c7c31fb0667249311",
          "wordpress_logged_in_1beb83a295a571198e9b4ecc05e58d1b": "3m0dpwcqzi%7C1763122602%7CHRz1C5gLE0G1xJE0ihchxMIngg9XzxvkSwrgFdxZPNQ%7C65579400452fb4e3ff4803a6919f0a535fa8029a5e1d24331bdf04857fa535ad"
        },
        "payment_count": 2,
        "mode": "rotate",
        "raw_cookies": {
          "wordpress_sec_1beb83a295a571198e9b4ecc05e58d1b": "3m0dpwcqzi%7C1763122602%7CHRz1C5gLE0G1xJE0ihchxMIngg9XzxvkSwrgFdxZPNQ%7Cc275c7310d518e33ff8ac7658b5fe360766c844e8f88678c7c31fb0667249311",
          "wordpress_logged_in_1beb83a295a571198e9b4ecc05e58d1b": "3m0dpwcqzi%7C1763122602%7CHRz1C5gLE0G1xJE0ihchxMIngg9XzxvkSwrgFdxZPNQ%7C65579400452fb4e3ff4803a6919f0a535fa8029a5e1d24331bdf04857fa535ad"
        },
        "cookies_valid": false
      },
      "https://www.theivannadrink.com": {
        "accounts": [
          {
            "email": "ejr4q6osvz@gmail.com",
            "username": "user_5dh4lnih",
            "password": "07amv7g06n3f"
          }
        ],
        "cookies": {
          "wordpress_sec_63c250a8023763cd908e881e3798c562": "ejr4q6osvz%7C1763121928%7CZOPExL4zrACQgHYKmNKZre0mMLVws3cTMKvJSCCYZko%7C3915067c2dda2906114249d332a9195747b27d02c44cf8fb7c585fc773949295",
          "wordpress_logged_in_63c250a8023763cd908e881e3798c562": "ejr4q6osvz%7C1763121928%7CZOPExL4zrACQgHYKmNKZre0mMLVws3cTMKvJSCCYZko%7Cddd8ffd55cd1237514a7369313062961dfa2cd0d1d89ca01f4124e6bbc86d29e"
        },
        "payment_count": 3,
        "mode": "rotate",
        "raw_cookies": {
          "wordpress_sec_63c250a8023763cd908e881e3798c562": "ejr4q6osvz%7C1763121928%7CZOPExL4zrACQgHYKmNKZre0mMLVws3cTMKvJSCCYZko%7C3915067c2dda2906114249d332a9195747b27d02c44cf8fb7c585fc773949295",
          "wordpress_logged_in_63c250a8023763cd908e881e3798c562": "ejr4q6osvz%7C1763121928%7CZOPExL4zrACQgHYKmNKZre0mMLVws3cTMKvJSCCYZko%7Cddd8ffd55cd1237514a7369313062961dfa2cd0d1d89ca01f4124e6bbc86d29e"
        },
        "cookies_valid": true,
        "stripe_pk": "pk_live_51NMrwuEaZ1IMBx9SXXuYsi4PWxCn5pXg2y7nJWbBE9gvHjFRPpbl56TkTHKZven06eiqNOGK7MJivlEA2KPBFfCS00ld4CxbiO",
        "stripe_nonce": "9a7624e04d"
      },
      "https://computer.com": {
        "accounts": [
          {
            "email": "p0mljy34ud@gmail.com",
            "username": "user_xy1j4iia",
            "password": "knl85m2z70uo"
          }
        ],
        "cookies": {},
        "payment_count": 3,
        "mode": "rotate",
        "raw_cookies": {},
        "stripe_pk": "pk_live_51JCX6TKkoB1IFgEIXuHBziCgyTCsd5Q9QU4YEnpfh4NTLsvRGgpq3rh3N8WMHxHRWXgOibSYdoY0wQ3lqIxGEDRm00kUwmSuAM",
        "stripe_nonce": "b8ded915e2"
      },
      "https://reginamode.it": {
        "accounts": [],
        "cookies": null,
        "payment_count": 1,
        "mode": "rotate"
      },
      "https://bitlantis.city": {
        "accounts": [
          {
            "email": "2ioiyc6z9e@gmail.com",
            "username": "user_ztlc1vl3",
            "password": "u5ufzorrppft"
          }
        ],
        "cookies": {
          "wordpress_sec_9e52aae66c9d864bac64189d1a3f76d1": "2ioiyc6z9e%7C1763121937%7CoTdmxMUr3vJnK31jUUEec3DZDGCzJkh79E2JsjBN9DS%7Cdbb38e7c9b40fbce0e639b211f8c56452e2d1651705a5462a212b7659407cffc",
          "wordpress_logged_in_9e52aae66c9d864bac64189d1a3f76d1": "2ioiyc6z9e%7C1763121937%7CoTdmxMUr3vJnK31jUUEec3DZDGCzJkh79E2JsjBN9DS%7C8df15c87a945552b6a0bbece375efeeae6735f8ea1984a469074f10cf9c4996a",
          "wfwaf-authcookie-05d276858d3ffbd50083983f224bfde1": "910%7Cother%7Cread%7C05c524ab272a4fc78b246e40b1b979d7ee5e549fe6b60cfad67f5e4956f02373"
        },
        "payment_count": 5,
        "mode": "rotate",
        "raw_cookies": {
          "wordpress_sec_9e52aae66c9d864bac64189d1a3f76d1": "2ioiyc6z9e%7C1763121937%7CoTdmxMUr3vJnK31jUUEec3DZDGCzJkh79E2JsjBN9DS%7Cdbb38e7c9b40fbce0e639b211f8c56452e2d1651705a5462a212b7659407cffc",
          "wordpress_logged_in_9e52aae66c9d864bac64189d1a3f76d1": "2ioiyc6z9e%7C1763121937%7CoTdmxMUr3vJnK31jUUEec3DZDGCzJkh79E2JsjBN9DS%7C8df15c87a945552b6a0bbece375efeeae6735f8ea1984a469074f10cf9c4996a",
          "wfwaf-authcookie-05d276858d3ffbd50083983f224bfde1": "910%7Cother%7Cread%7C05c524ab272a4fc78b246e40b1b979d7ee5e549fe6b60cfad67f5e4956f02373"
        },
        "stripe_pk": "pk_live_51HntbqERRHb6iNfek4ceMaVg9yo5AFKvBOYu074eoYKoX4OOAvQRliFhqqEaS0vWcy8CVD9hyEeEakAe2nzmHqZR007EzdG1g9",
        "stripe_nonce": "1b924749d2",
        "cookies_valid": true
      },
      "https://directwastedisposal.com": {
        "accounts": [
          {
            "email": "37afzmrog7@gmail.com",
            "username": "user_eva8henu",
            "password": "kwvg1wrsb8uc"
          }
        ],
        "cookies": {
          "wordpress_sec_fbf8dd1744952518efde3b1572616c75": "37afzmrog7%7C1763121728%7ChVyLoxMExmMAKNkJVbkPVxarApBIBgk01V0FVIyMX1e%7C210463457af58670998ca04067892ebd76b6f3d2fde1431cf5c7f949cb4e3cfe",
          "wordpress_logged_in_fbf8dd1744952518efde3b1572616c75": "37afzmrog7%7C1763121728%7ChVyLoxMExmMAKNkJVbkPVxarApBIBgk01V0FVIyMX1e%7Cef6221d29979906cd3cc2f85d4fe71ad484adb4a146cab34add4c6fb53fd3220"
        },
        "payment_count": 1,
        "mode": "rotate",
        "raw_cookies": {
          "wordpress_sec_fbf8dd1744952518efde3b1572616c75": "37afzmrog7%7C1763121728%7ChVyLoxMExmMAKNkJVbkPVxarApBIBgk01V0FVIyMX1e%7C210463457af58670998ca04067892ebd76b6f3d2fde1431cf5c7f949cb4e3cfe",
          "wordpress_logged_in_fbf8dd1744952518efde3b1572616c75": "37afzmrog7%7C1763121728%7ChVyLoxMExmMAKNkJVbkPVxarApBIBgk01V0FVIyMX1e%7Cef6221d29979906cd3cc2f85d4fe71ad484adb4a146cab34add4c6fb53fd3220"
        },
        "stripe_pk": "pk_live_ep6D8G90eBpgEcYSzSEF8FUp",
        "stripe_nonce": "8ca4d9360d"
      },
      "https://www.brosnapaints.ie": {
        "accounts": [
          {
            "email": "cafrlqzhez@gmail.com",
            "username": "user_wup6k713",
            "password": "5m9yy3hl9juf"
          }
        ],
        "cookies": {},
        "payment_count": 2,
        "mode": "rotate",
        "raw_cookies": {},
        "stripe_pk": "pk_live_ndEuZ1PIOyXfmL3ViEDCN2tc",
        "stripe_nonce": "cad6b74273"
      },
      "https://www.aureliaenergyhealing.com": {
        "accounts": [],
        "cookies": null,
        "payment_count": 0,
        "mode": "rotate"
      },
      "https://greenwoodtrack.co.uk": {
        "accounts": [],
        "cookies": null,
        "payment_count": 1,
        "mode": "rotate"
      },
      "https://mycustomscent.com": {
        "accounts": [
          {
            "email": "zd8didjg59@gmail.com",
            "username": "user_8rutipno",
            "password": "n3jzec23jql2"
          }
        ],
        "cookies": {
          "mailchimp_landing_site": "https%3A%2F%2Fmycustomscent.com%2Fmy-account%2F",
          "wordpress_logged_in_63e6ae0f474eb571c6dca04208e05cb3": "zd8didjg59%7C1763121790%7CvWpH0fqrbiy23IuZmRIfI3KCjuL5z8SFXHOY0v4iYBq%7C37a2e3d875203cc180fc56b5212f27ab794a11b1b8252b0c6f2a2b0784efc73c",
          "wordpress_sec_63e6ae0f474eb571c6dca04208e05cb3": "zd8didjg59%7C1763121790%7CvWpH0fqrbiy23IuZmRIfI3KCjuL5z8SFXHOY0v4iYBq%7Cb80c96a14c5ee60f8a9468bb42702c7fc45b6bf503f0f795efa6d0cf067151e5"
        },
        "payment_count": 3,
        "mode": "rotate",
        "raw_cookies": {
          "mailchimp_landing_site": "https%3A%2F%2Fmycustomscent.com%2Fmy-account%2F",
          "wordpress_logged_in_63e6ae0f474eb571c6dca04208e05cb3": "zd8didjg59%7C1763121790%7CvWpH0fqrbiy23IuZmRIfI3KCjuL5z8SFXHOY0v4iYBq%7C37a2e3d875203cc180fc56b5212f27ab794a11b1b8252b0c6f2a2b0784efc73c",
          "wordpress_sec_63e6ae0f474eb571c6dca04208e05cb3": "zd8didjg59%7C1763121790%7CvWpH0fqrbiy23IuZmRIfI3KCjuL5z8SFXHOY0v4iYBq%7Cb80c96a14c5ee60f8a9468bb42702c7fc45b6bf503f0f795efa6d0cf067151e5"
        },
        "stripe_pk": "pk_live_yIuFO0roV5FiZPhz81JwVpI9",
        "stripe_nonce": "b6dc01f5cd",
        "cookies_valid": true
      },
      "https://www.comfortq.it": {
        "accounts": [
          {
            "email": "r3shpekggz@gmail.com",
            "username": "user_70u03n5z",
            "password": "aar5uk1tz2t7"
          }
        ],
        "cookies": {
          "omnisendContactID": "6904a8d1c9fdfa969be47169",
          "wordpress_sec_ff2ca9a419b5b6f4a528c8ed5f09e52b": "r3shpekggz%7C1763122641%7CuoqBpUGY4hLEoGLMifnEidDATxIxfEdJOeON36NJJzN%7C6b3a203aa196a028a4e486b1f206ced74c1d36c11c98e0746e4bb12c2c69d331",
          "wordpress_logged_in_ff2ca9a419b5b6f4a528c8ed5f09e52b": "r3shpekggz%7C1763122641%7CuoqBpUGY4hLEoGLMifnEidDATxIxfEdJOeON36NJJzN%7Cece76590ef03024d5fd6b9abcdaad073a9f5d0be2427434991e7e488885dad25"
        },
        "payment_count": 1,
        "mode": "rotate",
        "raw_cookies": {
          "wordpress_sec_ff2ca9a419b5b6f4a528c8ed5f09e52b": "r3shpekggz%7C1763122641%7CuoqBpUGY4hLEoGLMifnEidDATxIxfEdJOeON36NJJzN%7C6b3a203aa196a028a4e486b1f206ced74c1d36c11c98e0746e4bb12c2c69d331",
          "wordpress_logged_in_ff2ca9a419b5b6f4a528c8ed5f09e52b": "r3shpekggz%7C1763122641%7CuoqBpUGY4hLEoGLMifnEidDATxIxfEdJOeON36NJJzN%7Cece76590ef03024d5fd6b9abcdaad073a9f5d0be2427434991e7e488885dad25"
        }
      },
      "https://rawnaturetreat.com": {
        "accounts": [],
        "cookies": null,
        "payment_count": 0,
        "mode": "rotate"
      },
      "https://tiga243land.com": {
        "accounts": [],
        "cookies": null,
        "payment_count": 0,
        "mode": "rotate"
      },
      "https://korinbagel.com": {
        "accounts": [],
        "cookies": null,
        "payment_count": 1,
        "mode": "rotate"
      },
      "https://cocokaboo.com.au": {
        "accounts": [],
        "cookies": null,
        "payment_count": 0,
        "mode": "rotate"
      },
      "https://dev.correctionslifeskills.com": {
        "accounts": [],
        "cookies": null,
        "payment_count": 1,
        "mode": "rotate"
      },
      "https://foodoftitans.com": {
        "accounts": [
          {
            "email": "k0qrjtu7oh@gmail.com",
            "username": "user_f9biuq9l",
            "password": "3seykmiegk0m"
          }
        ],
        "cookies": {
          "_lscache_vary": "358d77b38e0e577451e8a6b1316b4292",
          "wordpress_logged_in_c54b70272073040a17f7ad63acfc4796": "user_f9biuq9l%7C1763122122%7CP4uThHEsmxXz3c6DM7Qbyk0iVGkzJtiFunjaDlyqcpN%7Caa886e755304331ac3f45ed5e2dac3f0199910ee22bf0aa3c98e5c7b1dbc1630",
          "wordpress_sec_c54b70272073040a17f7ad63acfc4796": "user_f9biuq9l%7C1763122122%7CP4uThHEsmxXz3c6DM7Qbyk0iVGkzJtiFunjaDlyqcpN%7Ce54488304acff46a6b918ea9a245e5c17f55b944e3c021d2d106f45dcd48b511"
        },
        "payment_count": 1,
        "mode": "rotate",
        "raw_cookies": {
          "_lscache_vary": "358d77b38e0e577451e8a6b1316b4292",
          "wordpress_logged_in_c54b70272073040a17f7ad63acfc4796": "user_f9biuq9l%7C1763122122%7CP4uThHEsmxXz3c6DM7Qbyk0iVGkzJtiFunjaDlyqcpN%7Caa886e755304331ac3f45ed5e2dac3f0199910ee22bf0aa3c98e5c7b1dbc1630",
          "wordpress_sec_c54b70272073040a17f7ad63acfc4796": "user_f9biuq9l%7C1763122122%7CP4uThHEsmxXz3c6DM7Qbyk0iVGkzJtiFunjaDlyqcpN%7Ce54488304acff46a6b918ea9a245e5c17f55b944e3c021d2d106f45dcd48b511"
        },
        "stripe_pk": "pk_test_51PKjlMH3bwH2JbZL5yPgu9HVnI5OB2lc8Nmohpi6VyVb0EjYOSvSWqUdvpvwQtffzGXbHaMC9PGkx5TLlDVGsmGA00A9JfLeja",
        "stripe_nonce": "d50062f8d6"
      },
      "https://flinttownunited.co.uk": {
        "accounts": [
          {
            "email": "dhzky2inmg@gmail.com",
            "username": "user_7bqicgub",
            "password": "imnee167lysn"
          }
        ],
        "cookies": {
          "PHPSESSID": "7s8p9d5beltp84p83adrspi2ts"
        },
        "payment_count": 2,
        "mode": "rotate",
        "raw_cookies": {
          "PHPSESSID": "7s8p9d5beltp84p83adrspi2ts"
        },
        "stripe_pk": "pk_live_51K40cfFTlGq5WUbBAUfCzvtdvVQTshbVbPncy0tQPPJEoavnlRe2mo7DnEWuKOzQSHD1LNqdu2xwemlwlmbSOiav00QnVSoNvt",
        "stripe_nonce": "18fc06f68d",
        "cookies_valid": true
      },
      "https://k33b.com": {
        "accounts": [],
        "cookies": null,
        "payment_count": 0,
        "mode": "rotate"
      },
      "https://www.ghananaturals.com": {
        "accounts": [
          {
            "email": "c6jdqbey0d@gmail.com",
            "username": "user_49xylyr1",
            "password": "cdwmnkd06dn0"
          }
        ],
        "cookies": {
          "mailchimp_landing_site": "https%3A%2F%2Fwww.ghananaturals.com%2Fmy-account%2F"
        },
        "payment_count": 3,
        "mode": "rotate",
        "raw_cookies": {
          "mailchimp_landing_site": "https%3A%2F%2Fwww.ghananaturals.com%2Fmy-account%2F"
        },
        "stripe_pk": "pk_live_51P4uf9JVeKYC5eeEbjlXMa0TdF8jKs6JqZW3g9d2Umiw21BCQQzry3FQSOerNey5z4DXnUQtvtA24OA7tvnFGC1V00XsSC3QqK",
        "stripe_nonce": "b6d8e79fa6",
        "cookies_valid": true
      },
      "https://mathraboud.ae": {
        "accounts": [
          {
            "email": "zs9erhfzb9@gmail.com",
            "username": "user_1qkf0kbr",
            "password": "z57mcxslkbry"
          }
        ],
        "cookies": {},
        "payment_count": 3,
        "mode": "rotate",
        "raw_cookies": {},
        "stripe_pk": "pk_test_51PP2feF6nm8rogBmr3IHVXK4i4EHR4EGyJw4ayPBia8ZKNitBlIvt9wqPJcbXxr46TgIiOP7uE4QFTyMQV0b9xS700AqyFwmIh",
        "stripe_nonce": "44938e2c30"
      },
      "https://artibox.com.sg": {
        "accounts": [
          {
            "email": "3vn8ymh689@gmail.com",
            "username": "user_coanqzts",
            "password": "gximax0w2yu4"
          }
        ],
        "cookies": {
          "wordpress_sec_1b0cde87750fbbb02777e1f5ccfb3a7f": "user_coanqzts%7C1763122346%7Cnqp44eJa12KWVTaeWe13pei5zywNFDjTk9X0ieJqYRC%7C08a4322c1056e37f0c09d9ab3cc7c642897bb992bf4e05f3febd43183cbdf04e",
          "wordpress_logged_in_1b0cde87750fbbb02777e1f5ccfb3a7f": "user_coanqzts%7C1763122346%7Cnqp44eJa12KWVTaeWe13pei5zywNFDjTk9X0ieJqYRC%7C3eacfb2c4bb285c3772683648ff5c3dba0b6e7ddea8b6b55505bd78ba74b9c32",
          "wfwaf-authcookie-1b0cde87750fbbb02777e1f5ccfb3a7f": "3708%7Cother%7Cread%7Cb619cc39ea19e994ea42fc0ee805ee1e995d06c97c5fe15ab19652a473bcf031"
        },
        "payment_count": 1,
        "mode": "rotate",
        "raw_cookies": {
          "wordpress_sec_1b0cde87750fbbb02777e1f5ccfb3a7f": "user_coanqzts%7C1763122346%7Cnqp44eJa12KWVTaeWe13pei5zywNFDjTk9X0ieJqYRC%7C08a4322c1056e37f0c09d9ab3cc7c642897bb992bf4e05f3febd43183cbdf04e",
          "wordpress_logged_in_1b0cde87750fbbb02777e1f5ccfb3a7f": "user_coanqzts%7C1763122346%7Cnqp44eJa12KWVTaeWe13pei5zywNFDjTk9X0ieJqYRC%7C3eacfb2c4bb285c3772683648ff5c3dba0b6e7ddea8b6b55505bd78ba74b9c32",
          "wfwaf-authcookie-1b0cde87750fbbb02777e1f5ccfb3a7f": "3708%7Cother%7Cread%7Cb619cc39ea19e994ea42fc0ee805ee1e995d06c97c5fe15ab19652a473bcf031"
        },
        "stripe_pk": "pk_test_51INp77C23Z3yzlODfS7XcEejCjLPWbDsuO5jGwPVKT4WCPGpCmQL7iGJiYGvnrpwIBV2UyM2RGDaFo5du4rNgLRm00OsfoJzeV",
        "stripe_nonce": "3eb66378d9"
      },
      "https://alquds.pk": {
        "accounts": [
          {
            "email": "0ia6r5ipdv@gmail.com",
            "username": "user_255jp1a7",
            "password": "p1pfhfy5k02p"
          }
        ],
        "cookies": {
          "PHPSESSID": "ffbf3dcb2d144ef54c79f032f41469ed"
        },
        "payment_count": 1,
        "mode": "rotate",
        "raw_cookies": {
          "PHPSESSID": "ffbf3dcb2d144ef54c79f032f41469ed"
        }
      },
      "https://store.astrinsurgical.com": {
        "accounts": [],
        "cookies": null,
        "payment_count": 0,
        "mode": "rotate"
      },
      "https://ozencare.com": {
        "accounts": [
          {
            "email": "ariifk3lig@gmail.com",
            "username": "user_8vzaz6ok",
            "password": "wb86wpu361xq"
          }
        ],
        "cookies": {},
        "payment_count": 2,
        "mode": "rotate",
        "raw_cookies": {},
        "stripe_pk": "pk_live_51LEHdEIh9j8VoRPSqBlSg9BracRkGh58URqMFRSxXf5Ua1gloX5Y8xR5QQvKe5U9jubn6P3cUq9VGNfPiDh5hzA700S3Kh9rae",
        "stripe_nonce": "b513e435f6"
      },
      "https://browart23.com": {
        "accounts": [
          {
            "email": "a8oncb9u2g@gmail.com",
            "username": "user_vdn4u47p",
            "password": "tt7gpu24otj2"
          }
        ],
        "cookies": {
          "wordpress_sec_216f05fb529806a975d62dae9b131a49": "user_vdn4u47p%7C1763122449%7C3X7zpkNBDVwz5Bn5TYNQRMX2CgmsAf8NzmRlvJ68Mc4%7Cccc3cdbdbed5c48c8a13b4a28bb972f08372c51f1613efe2db5b76ca21cc4377",
          "wordpress_logged_in_216f05fb529806a975d62dae9b131a49": "user_vdn4u47p%7C1763122449%7C3X7zpkNBDVwz5Bn5TYNQRMX2CgmsAf8NzmRlvJ68Mc4%7Cefc0b742278d773c1d168de80176396f48ab8cbe4a1a0afd3a062169d53e9972"
        },
        "payment_count": 3,
        "mode": "rotate",
        "raw_cookies": {
          "wordpress_sec_216f05fb529806a975d62dae9b131a49": "user_vdn4u47p%7C1763122449%7C3X7zpkNBDVwz5Bn5TYNQRMX2CgmsAf8NzmRlvJ68Mc4%7Cccc3cdbdbed5c48c8a13b4a28bb972f08372c51f1613efe2db5b76ca21cc4377",
          "wordpress_logged_in_216f05fb529806a975d62dae9b131a49": "user_vdn4u47p%7C1763122449%7C3X7zpkNBDVwz5Bn5TYNQRMX2CgmsAf8NzmRlvJ68Mc4%7Cefc0b742278d773c1d168de80176396f48ab8cbe4a1a0afd3a062169d53e9972"
        },
        "stripe_pk": "pk_test_51POgZVG6RqUlHmzYL3xqZXSq71nEE2tgNyrkFgcpOZs7s2sTPsYgEDKDBouNhG6FMA0zbBNSslOSQQHXWHHV7ajh00wqxtBtxp",
        "stripe_nonce": "168accbad5",
        "cookies_valid": true
      },
      "https://thebeautyshaman.com": {
        "accounts": [
          {
            "email": "53qb90oen4@gmail.com",
            "username": "user_b5la2y27",
            "password": "2wky555t8rdm"
          }
        ],
        "cookies": {
          "mailchimp_landing_site": "https%3A%2F%2Fthebeautyshaman.com%2Fmy-account%2F",
          "wordpress_logged_in_caaa0c203d8a04b2e3be4fccfda9d4e7": "53qb90oen4%7C1763123064%7CxpjdAtuKUBDz14n3TNyO1kSScxJZbGA1e04wRk674kd%7Cbc2c957bf8dd7194a7d70e71e6ec3dc2c0f46bb7ddfd9baa421e460578f1d4a4",
          "wfwaf-authcookie-038557bf46a6f9cad54d0eb29f7b0209": "2524%7Cother%7Cread%7C865d1cf95ea1b0bc6cace4e10f00d748cf5d22243e5388b2faae81f4e4d31091",
          "wordpress_sec_caaa0c203d8a04b2e3be4fccfda9d4e7": "53qb90oen4%7C1763123064%7CxpjdAtuKUBDz14n3TNyO1kSScxJZbGA1e04wRk674kd%7C176c750f125f1a23a015aba8c1fb922feac79d8d08bc33ea7aae23614858f1dc"
        },
        "payment_count": 1,
        "mode": "rotate",
        "raw_cookies": {
          "mailchimp_landing_site": "https%3A%2F%2Fthebeautyshaman.com%2Fmy-account%2F",
          "wordpress_logged_in_caaa0c203d8a04b2e3be4fccfda9d4e7": "53qb90oen4%7C1763123064%7CxpjdAtuKUBDz14n3TNyO1kSScxJZbGA1e04wRk674kd%7Cbc2c957bf8dd7194a7d70e71e6ec3dc2c0f46bb7ddfd9baa421e460578f1d4a4",
          "wfwaf-authcookie-038557bf46a6f9cad54d0eb29f7b0209": "2524%7Cother%7Cread%7C865d1cf95ea1b0bc6cace4e10f00d748cf5d22243e5388b2faae81f4e4d31091",
          "wordpress_sec_caaa0c203d8a04b2e3be4fccfda9d4e7": "53qb90oen4%7C1763123064%7CxpjdAtuKUBDz14n3TNyO1kSScxJZbGA1e04wRk674kd%7C176c750f125f1a23a015aba8c1fb922feac79d8d08bc33ea7aae23614858f1dc"
        }
      },
      "https://hazlomemorable.com": {
        "accounts": [],
        "cookies": null,
        "payment_count": 1,
        "mode": "rotate"
      },
      "https://foundmybrave.com": {
        "accounts": [
          {
            "email": "be2uluxyrk@gmail.com",
            "username": "user_5zodlf2x",
            "password": "75pfhuzc5twa"
          }
        ],
        "cookies": {
          "PHPSESSID": "mkv4jrlj4eoaefgn7hht0ebabv",
          "tk_ai": "jetpack%3ApwqgPCyQa8F4hZQdJJ64avGh"
        },
        "payment_count": 2,
        "mode": "rotate",
        "raw_cookies": {
          "PHPSESSID": "mkv4jrlj4eoaefgn7hht0ebabv",
          "tk_ai": "jetpack%3ApwqgPCyQa8F4hZQdJJ64avGh"
        },
        "stripe_pk": "pk_live_51KmKidEUDfmbUEy8zNbqiHhbG1gOETaR7dV2x9e3bCJ4mYkoDP1j6O71YeVVPlqsYYXXkn55fdkIxa4ihRcRd7Yu00SLZx5aBc",
        "stripe_nonce": "819d32d566",
        "cookies_valid": true
      },
      "https://thurstonprintlab.biz": {
        "accounts": [
          {
            "email": "orfywoeakd@gmail.com",
            "username": "user_v8uosg1x",
            "password": "0ydsz62hfdgv"
          }
        ],
        "cookies": {},
        "payment_count": 1,
        "mode": "rotate",
        "raw_cookies": {}
      }
    }
  }
}